.DS_Store
cloudmlmagic/__init__.py
cloudmlmagic/cloudmlmagic.py
cloudmlmagic-0.0.5.dist-info/DESCRIPTION.rst
cloudmlmagic-0.0.5.dist-info/METADATA
cloudmlmagic-0.0.5.dist-info/RECORD
cloudmlmagic-0.0.5.dist-info/WHEEL
cloudmlmagic-0.0.5.dist-info/metadata.json
cloudmlmagic-0.0.5.dist-info/top_level.txt
