Metadata-Version: 2.0
Name: cloudmlmagic
Version: 0.0.5
Summary: Jupyter Notebook Magics for Google Cloud ML Engine
Home-page: https://github.com/hayatoy/cloudml-magic
Author: Hayato Yoshikawa
Author-email: UNKNOWN
License: MIT
Platform: UNKNOWN
Requires-Dist: google-api-python-client
